lab7/full_adder.v
module full_adder(
    input A, B, Cin,
    output Y, Cout
);

    assign Y = A ^ B ^ Cin;
    assign Cout = (B & Cin) | (A & B) | (A & Cin);

endmodule
// Implement module called full_adder

lab6/class/adder.v
module adder(
    // Declare your A/B inputs
    input A, B,
    // Declare Y output
    output Y,
    // Declare carry output
    output carry
);

    assign Y = A ^ B;
    assign carry = A & B;
    
    
endmodule

lab6/class/light.v
module light(
    input down, up, // 0 is downstairs, 1 is upstairs
    output light //lightbulb
);

    assign light = up ^ down;
endmodule

lab6/class/top.v
module top(
    input [7:0] sw,
    output [5:0] led
);

    light light(
        .down(sw[0]),
        .up(sw[1]),
        .light(led[0])
    );
    
    adder a (
        .A(sw[2]),
        .B(sw[3]),
        .Y(led[1]),
        .carry(led[2])
     );
     
    wire carry;
    
    full_adder FA1 (
        .A(sw[4]),
        .B(sw[6]),
        .Cin(0),
        .Y(led[3]),
        .Cout(carry)
    );
    
    full_adder FA2 (
        .A(sw[5]),
        .B(sw[7]),
        .Cin(carry),
        .Y(led[4]),
        .Cout(led[5])
    );

endmodule

lab6/class/test.v
`timescale 10ns/1ns

module test;

    reg [7:0] sw;
    wire [4:0] led;

    generate
        genvar led_idx;

        for (led_idx = 0; led_idx <= 4; led_idx = led_idx + 1) begin
            pulldown(led[led_idx]);
        end
    endgenerate

    top uut(
        .sw(sw[7:0]),
        .led(led[4:0])
    );

    initial begin
    
        $dumpvars(0, test);
        sw[0] = 0;
        sw[1] = 0;
        sw[2] = 0;
        sw[3] = 0;
        sw[4] = 0;
        sw[5] = 0;
        sw[6] = 0;
        sw[7] = 0;
        #20;
        if (led != 5'b00000) begin
            $display("Test failed! 01");
            $finish;
        end
        sw[0] = 0;
        sw[1] = 1;
        sw[2] = 1;
        sw[3] = 0;
        sw[4] = 1;
        sw[5] = 0;
        sw[6] = 0;
        sw[7] = 0;
        #20;
        if (led != 5'b01011) begin
            $display("Test failed! 02");
            $finish;
        end
        sw[0] = 1;
        sw[1] = 0;
        sw[2] = 0;
        sw[3] = 1;
        sw[4] = 0;
        sw[5] = 1;
        sw[6] = 0;
        sw[7] = 0;
        #20;
        if (led != 5'b10011) begin
            $display("Test failed! 03");
            $finish;
        end
        sw[0] = 1;
        sw[1] = 1;
        sw[2] = 1;
        sw[3] = 1;
        sw[4] = 1;
        sw[5] = 1;
        sw[6] = 0;
        sw[7] = 0;
        #20;
        if (led != 5'b11100) begin
            $display("Test failed! 04");
            $finish;
        end
        sw[4] = 0;
        sw[5] = 0;
        sw[6] = 1;
        sw[7] = 0;
        #20;
        if (led != 5'b01100) begin
            $display("Test failed! 05");
            $finish;
        end
        sw[4] = 1;
        sw[5] = 0;
        sw[6] = 1;
        sw[7] = 0;
        #20;
        if (led != 5'b10100) begin
            $display("Test failed! 06");
            $finish;
        end
        sw[4] = 0;
        sw[5] = 1;
        sw[6] = 1;
        sw[7] = 0;
        #20;
        if (led != 5'b11100) begin
            $display("Test failed! 07");
            $finish;
        end
        sw[4] = 1;
        sw[5] = 1;
        sw[6] = 1;
        sw[7] = 0;
        #20;
        if (led != 5'b00100) begin
            $display("Test failed! 08");
            $finish;
        end
        sw[4] = 0;
        sw[5] = 0;
        sw[6] = 0;
        sw[7] = 1;
        #20;
        if (led != 5'b10100) begin
            $display("Test failed! 09");
            $finish;
        end

        sw[4] = 1;
        sw[5] = 0;
        sw[6] = 0;
        sw[7] = 1;
        #20;
        if (led != 5'b11100) begin
            $display("Test failed! 10");
            $finish;
        end
        sw[4] = 0;
        sw[5] = 1;
        sw[6] = 0;
        sw[7] = 1;
        #20;
        if (led != 5'b00100) begin
            $display("Test failed! 11");
            $finish;
        end
        sw[4] = 1;
        sw[5] = 1;
        sw[6] = 0;
        sw[7] = 1;
        #20;
        if (led != 5'b01100) begin
            $display("Test failed! 12");
            $finish;
        end
        sw[4] = 0;
        sw[5] = 0;
        sw[6] = 1;
        sw[7] = 1;
        #20;
        if (led != 5'b11100) begin
            $display("Test failed! 13");
            $finish;
        end
        sw[4] = 1;
        sw[5] = 0;
        sw[6] = 1;
        sw[7] = 1;
        #20;
        if (led != 5'b00100) begin
            $display("Test failed! 14");
            $finish;
        end
        sw[4] = 0;
        sw[5] = 1;
        sw[6] = 1;
        sw[7] = 1;
        #20;
        if (led != 5'b01100) begin
            $display("Test failed! 15");
            $finish;
        end
        sw[4] = 1;
        sw[5] = 1;
        sw[6] = 1;
        sw[7] = 1;
        #20;
        if (led != 5'b10100) begin
            $display("Test failed! 16");
            $finish;
        end
        $display("Test passed!!");
        $finish;
    end
endmodule

lab6/lab6.sim/sim_1/behav/xsim/dump.vcd
$date
   Fri Oct  3 08:19:26 2025
$end

$version
  2023.2
$end

$timescale
  1ps
$end

$scope module test $end
$var reg 8 ! sw [7:0] $end
$var wire 5 " led [4:0] $end
$scope module uut $end
$var wire 8 # sw [7:0] $end
$var wire 6 $ led [5:0] $end
$var wire 1 % carry $end
$scope module light $end
$var wire 1 & down $end
$var wire 1 & up $end
$var wire 1 ' light $end
$upscope $end
$scope module a $end
$var wire 1 & A $end
$var wire 1 & B $end
$var wire 1 ' Y $end
$var wire 1 ' carry $end
$upscope $end
$scope module FA1 $end
$var wire 1 & A $end
$var wire 1 & B $end
$var wire 1 ( Cin $end
$var wire 1 ' Y $end
$var wire 1 % Cout $end
$upscope $end
$scope module FA2 $end
$var wire 1 ) A $end
$var wire 1 * B $end
$var wire 1 % Cin $end
$var wire 1 + Y $end
$var wire 1 , Cout $end
$upscope $end
$upscope $end
$upscope $end
$enddefinitions $end

#0
$dumpvars
b0 !
b0 "
b0 #
b0 $
0%
0&
0'
0(
0)
0*
0+
0,
$end

#200000
b10110 !
b1011 "
b10110 #
b1011 $
0&
1'
0)
0*

#400000
b101001 !
b10011 "
b101001 #
b10011 $
1&
1)
0*
1+

#600000
b111111 !
b11100 "
b111111 #
b11100 $
1&
0'
1)
0*

#800000
b1001111 !
b1100 "
b1001111 #
b1100 $
1&
0)
0*
0+

#1000000
b1011111 !
b10100 "
b1011111 #
b10100 $
1%
1&
0)
0*
1+

#1200000
b1101111 !
b11100 "
b1101111 #
b11100 $
0%
1&
1)
0*

#1400000
b1111111 !
b100 "
b1111111 #
b100100 $
1%
1&
1)
0*
0+
1,

#1600000
b10001111 !
b10100 "
b10001111 #
b10100 $
0%
1&
0)
1*
1+
0,

#1800000
b10011111 !
b11100 "
b10011111 #
b11100 $
1&
0)
1*

#2000000
b10101111 !
b100 "
b10101111 #
b100100 $
1&
1)
1*
0+
1,

#2200000
b10111111 !
b1100 "
b10111111 #
b101100 $
1&
1)
1*

#2400000
b11001111 !
b11100 "
b11001111 #
b11100 $
1&
0)
1*
1+
0,

#2600000
b11011111 !
b100 "
b11011111 #
b100100 $
1%
1&
0)
1*
0+
1,

#2800000
b11101111 !
b1100 "
b11101111 #
b101100 $
0%
1&
1)
1*

#3000000
b11111111 !
b10100 "
b11111111 #
b110100 $
1%
1&
1)
1*
1+
